fds/__init__.py
fds/sdk/__init__.py
fds/sdk/IRNConfiguration/__init__.py
fds/sdk/IRNConfiguration/api_client.py
fds/sdk/IRNConfiguration/configuration.py
fds/sdk/IRNConfiguration/exceptions.py
fds/sdk/IRNConfiguration/model_utils.py
fds/sdk/IRNConfiguration/rest.py
fds/sdk/IRNConfiguration/api/__init__.py
fds/sdk/IRNConfiguration/api/contacts___custom_fields_api.py
fds/sdk/IRNConfiguration/api/contacts___phone_number_types_api.py
fds/sdk/IRNConfiguration/api/contacts___relationship_category_api.py
fds/sdk/IRNConfiguration/api/contacts___relationships_api.py
fds/sdk/IRNConfiguration/api/contacts___roles_api.py
fds/sdk/IRNConfiguration/api/contacts___types_api.py
fds/sdk/IRNConfiguration/api/custom_symbols___custom_fields_api.py
fds/sdk/IRNConfiguration/api/custom_symbols___relationships_api.py
fds/sdk/IRNConfiguration/api/custom_symbols___types_api.py
fds/sdk/IRNConfiguration/api/notes___configuration_api.py
fds/sdk/IRNConfiguration/apis/__init__.py
fds/sdk/IRNConfiguration/model/__init__.py
fds/sdk/IRNConfiguration/model/approval_level_config_dto.py
fds/sdk/IRNConfiguration/model/approval_process_config_dto.py
fds/sdk/IRNConfiguration/model/author_config_dto.py
fds/sdk/IRNConfiguration/model/client_sales_representative_dto.py
fds/sdk/IRNConfiguration/model/commentary_config_dto.py
fds/sdk/IRNConfiguration/model/contact_custom_field_dto.py
fds/sdk/IRNConfiguration/model/contact_custom_field_formula_dto.py
fds/sdk/IRNConfiguration/model/contact_custom_field_option_dto.py
fds/sdk/IRNConfiguration/model/contact_custom_field_option_save_dto.py
fds/sdk/IRNConfiguration/model/contact_custom_field_save_dto.py
fds/sdk/IRNConfiguration/model/contact_custom_field_type.py
fds/sdk/IRNConfiguration/model/contact_role_dto.py
fds/sdk/IRNConfiguration/model/contact_type_dto.py
fds/sdk/IRNConfiguration/model/create_custom_symbol_custom_field_dto.py
fds/sdk/IRNConfiguration/model/custom_field_config_dto.py
fds/sdk/IRNConfiguration/model/custom_field_team_config_dto.py
fds.sdk.IRNConfiguration-1.1.2.dist-info/LICENSE
fds.sdk.IRNConfiguration-1.1.2.dist-info/METADATA
fds.sdk.IRNConfiguration-1.1.2.dist-info/WHEEL
fds.sdk.IRNConfiguration-1.1.2.dist-info/top_level.txt
fds.sdk.IRNConfiguration-1.1.2.dist-info/RECORD
